babel/__init__.py
babel/_compat.py
babel/core.py
babel/dates.py
babel/global.dat
babel/languages.py
babel/lists.py
babel/localedata.py
babel/numbers.py
babel/plural.py
babel/support.py
babel/units.py
babel/util.py
babel/locale-data/af.dat
babel/locale-data/af_NA.dat
babel/locale-data/af_ZA.dat
babel/locale-data/agq.dat
babel/locale-data/agq_CM.dat
babel/locale-data/ak.dat
babel/locale-data/ak_GH.dat
babel/locale-data/am.dat
babel/locale-data/am_ET.dat
babel/locale-data/ar.dat
babel/locale-data/ar_001.dat
babel/locale-data/ar_AE.dat
babel/locale-data/ar_BH.dat
babel/locale-data/ar_DJ.dat
babel/locale-data/ar_DZ.dat
babel/locale-data/ar_EG.dat
babel/locale-data/ar_EH.dat
babel/locale-data/ar_ER.dat
babel/locale-data/ar_IL.dat
babel/locale-data/ar_IQ.dat
babel/locale-data/ar_JO.dat
babel/locale-data/ar_KM.dat
babel/locale-data/ar_KW.dat
babel/locale-data/ar_LB.dat
babel/locale-data/ar_LY.dat
babel/locale-data/ar_MA.dat
babel/locale-data/ar_MR.dat
babel/locale-data/ar_OM.dat
babel/locale-data/ar_PS.dat
babel/locale-data/ar_QA.dat
babel/locale-data/ar_SA.dat
babel/locale-data/ar_SD.dat
babel/locale-data/ar_SO.dat
babel/locale-data/ar_SS.dat
babel/locale-data/ar_SY.dat
babel/locale-data/ar_TD.dat
babel/locale-data/ar_TN.dat
babel/locale-data/ar_YE.dat
babel/locale-data/as.dat
babel/locale-data/as_IN.dat
babel/locale-data/asa.dat
babel/locale-data/asa_TZ.dat
babel/locale-data/ast.dat
babel/locale-data/ast_ES.dat
babel/locale-data/az.dat
babel/locale-data/az_Cyrl.dat
babel/locale-data/az_Cyrl_AZ.dat
babel/locale-data/az_Latn.dat
babel/locale-data/az_Latn_AZ.dat
babel/locale-data/bas.dat
babel/locale-data/bas_CM.dat
babel/locale-data/be.dat
babel/locale-data/be_BY.dat
babel/locale-data/bem.dat
babel/locale-data/bem_ZM.dat
babel/locale-data/bez.dat
babel/locale-data/bez_TZ.dat
babel/locale-data/bg.dat
babel/locale-data/bg_BG.dat
babel/locale-data/bm.dat
babel/locale-data/bm_ML.dat
babel_edge-2.5.3.dist-info/LICENSE.txt
babel_edge-2.5.3.dist-info/METADATA
babel_edge-2.5.3.dist-info/RECORD
babel_edge-2.5.3.dist-info/WHEEL
babel_edge-2.5.3.dist-info/entry_points.txt
babel_edge-2.5.3.dist-info/top_level.txt
